mygeometrysunil/__init__.py
mygeometrysunil/circle.py
mygeometrysunil/rectangle.py
mygeometrysunil-0.3.dist-info/METADATA
mygeometrysunil-0.3.dist-info/WHEEL
mygeometrysunil-0.3.dist-info/top_level.txt
mygeometrysunil-0.3.dist-info/RECORD
