Metadata-Version: 2.1
Name: mygeometrysunil
Version: 0.3
Summary: I am ludoo king, Please share OTP here
Author: Sunil Kumar
